setup.py
django_drip.egg-info/PKG-INFO
django_drip.egg-info/SOURCES.txt
django_drip.egg-info/dependency_links.txt
django_drip.egg-info/requires.txt
django_drip.egg-info/top_level.txt
drip/__init__.py
drip/admin.py
drip/drips.py
drip/models.py
drip/tests.py
drip/utils.py
drip/views.py
drip/__pycache__/__init__.cpython-34.pyc
drip/__pycache__/admin.cpython-34.pyc
drip/__pycache__/drips.cpython-34.pyc
drip/__pycache__/models.cpython-34.pyc
drip/__pycache__/tests.cpython-34.pyc
drip/__pycache__/utils.cpython-34.pyc
drip/management/__init__.py
drip/management/__pycache__/__init__.cpython-34.pyc
drip/management/commands/__init__.py
drip/management/commands/send_drips.py
drip/migrations/0001_initial.py
drip/migrations/0002_auto__add_field_drip_from_email__add_field_drip_from_email_name__add_f.py
drip/migrations/0003_auto__add_field_drip_message_class.py
drip/migrations/__init__.py
drip/migrations/__pycache__/0001_initial.cpython-34.pyc
drip/migrations/__pycache__/0002_auto__add_field_drip_from_email__add_field_drip_from_email_name__add_f.cpython-34.pyc
drip/migrations/__pycache__/0003_auto__add_field_drip_message_class.cpython-34.pyc
drip/migrations/__pycache__/__init__.cpython-34.pyc
drip/templates/admin/drip/change_form.html
drip/templates/admin/drip/SentDrip/change_form.html
drip/templates/drip/timeline.html